{
  "videos": [
    {
      "id": "youtube_e1_NXWjmwhc",
      "youtube_id": "e1_NXWjmwhc",
      "source": "youtube",
      "title": "The Abel (not Nobel) Prize - Numberphile",
      "url": "https://www.youtube.com/watch?v=e1_NXWjmwhc",
      "thumbnail": "https://i.ytimg.com/vi/e1_NXWjmwhc/mqdefault.jpg",
      "author": "Numberphile",
      "duration": "",
      "duration_seconds": 0,
      "duration_badge": "",
      "views": "",
      "views_raw": 0,
      "danmaku": "",
      "likes": "",
      "likes_raw": 0,
      "category": "数学计算机",
      "description": "Numberphile creator Brady Haran sees Gerd Faltings receive the Abel Prize - and goes behind the scenes at this prestigious event in Norway. Playlist from the event (with the longer interviews) at https://www.youtube.com/playlist?list=PLt5AfwLFPxWL4w1j3Xc3hZekFUNHGHCfq\n\nAbel Prize website: https://ab",
      "published": 1780499492,
      "published_str": "2026-06-03",
      "embed_id": "e1_NXWjmwhc",
      "embed_src": "youtube",
      "summary": null,
      "favorited": false
    },
    {
      "id": "youtube_v8e-tYey7ts",
      "youtube_id": "v8e-tYey7ts",
      "source": "youtube",
      "title": "The Unsolved Lollipop Problem - Numberphile",
      "url": "https://www.youtube.com/watch?v=v8e-tYey7ts",
      "thumbnail": "https://i.ytimg.com/vi/v8e-tYey7ts/mqdefault.jpg",
      "author": "Numberphile",
      "duration": "",
      "duration_seconds": 0,
      "duration_badge": "",
      "views": "",
      "views_raw": 0,
      "danmaku": "",
      "likes": "",
      "likes_raw": 0,
      "category": "数学计算机",
      "description": "Featuring Neil Sloane - more details below. Gear Train (episode sponsor) is at https://www.metmo.co.uk/collections/gear-train with discount code NUMBERPHILE10OFF -- More links & stuff in full description below ↓↓↓\n\nMore Neil Sloane videos at: https://www.youtube.com/playlist?list=PLt5AfwLFPxWJXQqPe_",
      "published": 1779890426,
      "published_str": "2026-05-27",
      "embed_id": "v8e-tYey7ts",
      "embed_src": "youtube",
      "summary": null,
      "favorited": false
    },
    {
      "id": "youtube_UiX4CFIiegM",
      "youtube_id": "UiX4CFIiegM",
      "source": "youtube",
      "title": "Red & Black Knights (extraordinary result) - Numberphile",
      "url": "https://www.youtube.com/watch?v=UiX4CFIiegM",
      "thumbnail": "https://i.ytimg.com/vi/UiX4CFIiegM/mqdefault.jpg",
      "author": "Numberphile",
      "duration": "",
      "duration_seconds": 0,
      "duration_badge": "",
      "views": "",
      "views_raw": 0,
      "danmaku": "",
      "likes": "",
      "likes_raw": 0,
      "category": "数学计算机",
      "description": "Featuring Neil Sloane, founder of the OEIS... See the extra patterns and variations (including three knights) at https://youtu.be/VgmDuBCayPw\nMore links & stuff in full description below ↓↓↓\n\nWith thanks also to Jonas Karlsson - https://jonka364.github.io/\n\nNeil Sloane is the founder of the On-Line ",
      "published": 1778591101,
      "published_str": "2026-05-12",
      "embed_id": "UiX4CFIiegM",
      "embed_src": "youtube",
      "summary": null,
      "favorited": false
    },
    {
      "id": "youtube_SAtFZPtbMpI",
      "youtube_id": "SAtFZPtbMpI",
      "source": "youtube",
      "title": "Entirely Ridiculously Big Numbers - Numberphile",
      "url": "https://www.youtube.com/watch?v=SAtFZPtbMpI",
      "thumbnail": "https://i.ytimg.com/vi/SAtFZPtbMpI/mqdefault.jpg",
      "author": "Numberphile",
      "duration": "",
      "duration_seconds": 0,
      "duration_badge": "",
      "views": "",
      "views_raw": 0,
      "danmaku": "",
      "likes": "",
      "likes_raw": 0,
      "category": "数学计算机",
      "description": "Rubik's Cube combinations quickly lead to some unimaginably large numbers. More links & stuff in full description below ↓↓↓\n\nExtra footage on odd-numbered cubes: https://youtu.be/CTb7RyTwoQ0\n\nFeaturing Richard Elwes. More Richard on Numberphile: https://www.youtube.com/playlist?list=PLt5AfwLFPxWI42W",
      "published": 1777900325,
      "published_str": "2026-05-04",
      "embed_id": "SAtFZPtbMpI",
      "embed_src": "youtube",
      "summary": null,
      "favorited": false
    },
    {
      "id": "youtube_UfP83M07s24",
      "youtube_id": "UfP83M07s24",
      "source": "youtube",
      "title": "Mathematician Attempts Art - Numberphile",
      "url": "https://www.youtube.com/watch?v=UfP83M07s24",
      "thumbnail": "https://i.ytimg.com/vi/UfP83M07s24/mqdefault.jpg",
      "author": "Numberphile",
      "duration": "",
      "duration_seconds": 0,
      "duration_badge": "",
      "views": "",
      "views_raw": 0,
      "danmaku": "",
      "likes": "",
      "likes_raw": 0,
      "category": "数学计算机",
      "description": "Hannah Fry returns to Numberphile to showcase her art skills (and show us her new portrait at The Royal Society). See the Objectivity video (for more about the REAL artwork) at https://youtu.be/3HLxB5LbrDU\nMore links & stuff in full description below ↓↓↓\n\n(Real) artist Chloe Barnes can be found at: ",
      "published": 1776176837,
      "published_str": "2026-04-14",
      "embed_id": "UfP83M07s24",
      "embed_src": "youtube",
      "summary": null,
      "favorited": false
    }
  ],
  "_ts": 1780578811.099412
}